{"errors":[{"message":"Timeout: Unspecified","locations":[{"line":57,"column":3}],"path":["user","result","smart_blocked_by"],"extensions":{"name":"TimeoutError","source":"Server","retry_after":0,"code":29,"kind":"ServiceLevel","tracing":{"trace_id":"e90edd7640b06667"}},"code":29,"kind":"ServiceLevel","name":"TimeoutError","source":"Server","retry_after":0,"tracing":{"trace_id":"e90edd7640b06667"}},{"message":"Timeout: Unspecified","locations":[{"line":58,"column":3}],"path":["user","result","smart_blocking"],"extensions":{"name":"TimeoutError","source":"Server","retry_after":0,"code":29,"kind":"ServiceLevel","tracing":{"trace_id":"e90edd7640b06667"}},"code":29,"kind":"ServiceLevel","name":"TimeoutError","source":"Server","retry_after":0,"tracing":{"trace_id":"e90edd7640b06667"}},{"message":"Timeout: Unspecified","locations":[{"line":59,"column":3}],"path":["user","result","smart_blocking_expiration"],"extensions":{"name":"TimeoutError","source":"Server","retry_after":0,"code":29,"kind":"ServiceLevel","tracing":{"trace_id":"e90edd7640b06667"}},"code":29,"kind":"ServiceLevel","name":"TimeoutError","source":"Server","retry_after":0,"tracing":{"trace_id":"e90edd7640b06667"}}],"data":{"user":{"result":{"__typename":"User","id":"VXNlcjoxMjgyMDExNDUxNDg2NTAyOTEy","rest_id":"1282011451486502912","affiliates_highlighted_label":{},"has_graduated_access":true,"is_blue_verified":true,"profile_image_shape":"Circle","legacy":{"can_dm":true,"can_media_tag":false,"created_at":"Sat Jul 11 17:58:51 +0000 2020","default_profile":true,"default_profile_image":false,"description":"impermanence in orbit","entities":{"description":{"urls":[]}},"fast_followers_count":0,"favourites_count":75698,"followers_count":27327,"friends_count":1310,"has_custom_timelines":true,"is_translator":false,"listed_count":21,"location":"nomad","media_count":1754,"name":"matt","normal_followers_count":27327,"pinned_tweet_ids_str":["1839214383492153385"],"possibly_sensitive":false,"profile_banner_url":"https://pbs.twimg.com/profile_banners/1282011451486502912/1751194803","profile_image_url_https":"https://pbs.twimg.com/profile_images/1973126929428418560/WQRykTGi_normal.jpg","profile_interstitial_type":"","screen_name":"mattsdoormats","statuses_count":19151,"translator_type":"none","verified":false,"want_retweets":false,"withheld_in_countries":[]},"verified_phone_status":false,"legacy_extended_profile":{},"is_profile_translatable":false,"has_hidden_likes_on_profile":true,"has_hidden_subscriptions_on_profile":true,"verification_info":{"is_identity_verified":true,"reason":{"description":{"text":"This account is verified. Learn more","entities":[{"from_index":26,"to_index":36,"ref":{"url":"https://help.twitter.com/managing-your-account/about-twitter-verified-accounts","url_type":"ExternalUrl"}}]},"verified_since_msec":"1745579141395"}},"highlights_info":{"can_highlight_tweets":true,"highlighted_tweets":"8"},"business_account":{},"creator_subscriptions_count":0}}},"request":{"name":"UserByScreenName","version":"G3KGOASz96M-Qu0nwmGXNg","timestamp_ms":"1764462528033","variables":{"screen_name":"mattsdoormats","withSafetyModeUserFields":true,"withGrokTranslatedBio":null}}}
